pydantic_ai_litellm/__init__.py
pydantic_ai_litellm/litellm_model.py
pydantic_ai_litellm-0.2.2.dist-info/licenses/LICENSE
pydantic_ai_litellm-0.2.2.dist-info/METADATA
pydantic_ai_litellm-0.2.2.dist-info/WHEEL
pydantic_ai_litellm-0.2.2.dist-info/top_level.txt
pydantic_ai_litellm-0.2.2.dist-info/RECORD
