Metadata-Version: 2.4
Name: pydantic-ai-litellm
Version: 0.2.2
Summary: LiteLLM model integration for Pydantic AI framework - access 100+ LLM providers through a unified interface
Author-email: Mottakin <md.mottakin.chowdhury@gmail.com>
Maintainer-email: Mottakin <md.mottakin.chowdhury@gmail.com>
License-Expression: MIT
Project-URL: Homepage, https://github.com/mochow13/pydantic-ai-litellm
Project-URL: Documentation, https://github.com/mochow13/pydantic-ai-litellm#readme
Project-URL: Repository, https://github.com/mochow13/pydantic-ai-litellm
Project-URL: Bug Tracker, https://github.com/mochow13/pydantic-ai-litellm/issues
Keywords: pydantic,ai,llm,litellm,openai,claude,gemini,machine-learning
Classifier: Development Status :: 4 - Beta
Classifier: Intended Audience :: Developers
Classifier: Programming Language :: Python :: 3
Classifier: Programming Language :: Python :: 3.13
Classifier: Topic :: Scientific/Engineering :: Artificial Intelligence
Classifier: Topic :: Software Development :: Libraries :: Python Modules
Classifier: Typing :: Typed
Requires-Python: >=3.13
License-File: LICENSE
Requires-Dist: litellm>=1.79.1
Requires-Dist: pydantic-ai-slim>=1.12.0
Dynamic: license-file
